LICENSE
MANIFEST.in
README.md
requirements.txt
setup.py
sse2fedmsg/__init__.py
sse2fedmsg.egg-info/PKG-INFO
sse2fedmsg.egg-info/SOURCES.txt
sse2fedmsg.egg-info/dependency_links.txt
sse2fedmsg.egg-info/entry_points.txt
sse2fedmsg.egg-info/not-zip-safe
sse2fedmsg.egg-info/requires.txt
sse2fedmsg.egg-info/top_level.txt